{"cameraMode":{"drawMode":0,"name":"Shaded","section":"Shading Mode"},"sceneLighting":false,"audioPlay":false,"sceneViewState":{"m_AlwaysRefresh":false,"showFog":true,"showSkybox":false,"showFlares":true,"showImageEffects":true,"showParticleSystems":true,"showVisualEffectGraphs":true,"m_FxEnabled":true},"in2DMode":false,"pivot":{"x":2.6001009941101076,"y":-0.4432893395423889,"z":-0.28209882974624636},"rotation":{"x":-0.19405943155288697,"y":-0.6561330556869507,"z":0.1800611913204193,"w":-0.706802248954773},"size":3.181086301803589,"orthographic":false}