{"cameraMode":{"drawMode":0,"name":"Shaded","section":"Shading Mode"},"sceneLighting":false,"audioPlay":false,"sceneViewState":{"m_AlwaysRefresh":false,"showFog":true,"showSkybox":false,"showFlares":true,"showImageEffects":true,"showParticleSystems":true,"showVisualEffectGraphs":true,"m_FxEnabled":true},"in2DMode":false,"pivot":{"x":4.010000228881836,"y":0.0,"z":0.0},"rotation":{"x":-0.038383450359106067,"y":-0.023705044761300088,"z":0.0008817213238216937,"w":-0.9990618228912354},"size":0.8660253882408142,"orthographic":false}